{
  "id": 52301,
  "registrationNumber": "CC11170",
  "name": "The New Zealand Federation of Voluntary Welfare Organisations Incorporated",
  "status": "Deregistered",
  "type": "1",
  "dateRegistered": "2007-09-19T00:00:00Z",
  "dateDeregistered": "2015-03-26T00:00:00Z",
  "website": "http://www.socialdevelopment.org.nz",
  "email": "ed@socialdevelopment.org.nz",
  "address": {
    "line1": "Level 4",
    "line2": "173-175 Victoria Street",
    "suburb": "Te Aro",
    "city": "Wellington",
    "postcode": "6011"
  },
  "nzbn": "9429042784791",
  "financialYearEnd": "30/6",
  "kaupapaMaori": null,
  "pasifika": null,
  "social": {
    "facebook": null,
    "twitter": null
  },
  "lastUpdated": "2018-01-09T00:34:50Z"
}