{
  "id": 55095,
  "registrationNumber": "CC22032",
  "name": "Gore And Districts Community Youth Worker Trust",
  "status": "Deregistered",
  "type": "0",
  "dateRegistered": "2008-03-19T00:00:00Z",
  "dateDeregistered": "2017-06-30T00:00:00Z",
  "website": null,
  "email": "gdcywt@gmail.com",
  "address": {
    "line1": "C/-",
    "line2": "1 Charlton Lane",
    "suburb": " ",
    "city": "Gore",
    "postcode": "9710"
  },
  "nzbn": "9429042631101",
  "financialYearEnd": "30/6",
  "kaupapaMaori": null,
  "pasifika": null,
  "social": {
    "facebook": null,
    "twitter": null
  },
  "lastUpdated": "2018-01-09T01:03:09Z"
}