{
  "id": 40174,
  "registrationNumber": "CC24208",
  "name": "The Kathleen Spragg Trust",
  "status": "Deregistered",
  "type": "0",
  "dateRegistered": "2008-05-11T00:00:00Z",
  "dateDeregistered": "2018-05-18T00:00:00Z",
  "website": null,
  "email": "gtcc@pgtrust.co.nz",
  "address": {
    "line1": "C/O NZ GUARDIAN TRUST",
    "line2": "Level 13, 191 Queen Street",
    "suburb": "Auckland Central",
    "city": "Auckland",
    "postcode": "1010"
  },
  "nzbn": null,
  "financialYearEnd": "30/11",
  "kaupapaMaori": null,
  "pasifika": null,
  "social": {
    "facebook": null,
    "twitter": null
  },
  "lastUpdated": "2018-06-13T01:57:16Z"
}