{
  "id": 41278,
  "registrationNumber": "CC24234",
  "name": "The Early Bird Foundation",
  "status": "Deregistered",
  "type": "0",
  "dateRegistered": "2008-05-11T00:00:00Z",
  "dateDeregistered": "2015-09-23T00:00:00Z",
  "website": null,
  "email": "sxc@martellimckegg.co.nz",
  "address": {
    "line1": "7 Hampton Drive",
    "line2": null,
    "suburb": "St Heliers",
    "city": "Auckland",
    "postcode": "1071"
  },
  "nzbn": null,
  "financialYearEnd": "31/3",
  "kaupapaMaori": null,
  "pasifika": null,
  "social": {
    "facebook": null,
    "twitter": null
  },
  "lastUpdated": "2018-01-09T01:18:08Z"
}