{
  "id": 41784,
  "registrationNumber": "CC24507",
  "name": "Te Hau Ora Kohanga Reo Trust",
  "status": "Deregistered",
  "type": "0",
  "dateRegistered": "2008-05-18T00:00:00Z",
  "dateDeregistered": "2014-12-16T00:00:00Z",
  "website": null,
  "email": "whanau@k02c016.kohanga.ac.nz",
  "address": {
    "line1": "8 Tamariki Avenue",
    "line2": null,
    "suburb": "Kelston",
    "city": "Auckland",
    "postcode": "602"
  },
  "nzbn": "9429042867081",
  "financialYearEnd": "31/12",
  "kaupapaMaori": null,
  "pasifika": null,
  "social": {
    "facebook": null,
    "twitter": null
  },
  "lastUpdated": "2018-01-09T01:20:09Z"
}