{
  "id": 55821,
  "registrationNumber": "CC24614",
  "name": "Taupo Revival Church Trust Board",
  "status": "Deregistered",
  "type": "0",
  "dateRegistered": "2008-05-20T00:00:00Z",
  "dateDeregistered": "2010-05-19T00:00:00Z",
  "website": null,
  "email": "donald@slingshot.co.nz",
  "address": {
    "line1": "62a Rotokawa Street",
    "line2": null,
    "suburb": null,
    "city": "Taupo",
    "postcode": "3330"
  },
  "nzbn": null,
  "financialYearEnd": "31/3",
  "kaupapaMaori": null,
  "pasifika": null,
  "social": {
    "facebook": null,
    "twitter": null
  },
  "lastUpdated": "2018-01-09T01:20:52Z"
}