{
  "id": 56776,
  "registrationNumber": "CC25224",
  "name": "Aotea (Great Barrier Island) Housing Trust",
  "status": "Deregistered",
  "type": "0",
  "dateRegistered": "2008-06-02T00:00:00Z",
  "dateDeregistered": "2017-01-23T00:00:00Z",
  "website": null,
  "email": "aawrightongbi@gmail.com",
  "address": {
    "line1": "C/- Angela Wright",
    "line2": "Puriri Bay Rd",
    "suburb": "Rd 1",
    "city": "Great Barrier Island",
    "postcode": null
  },
  "nzbn": "9429043127894",
  "financialYearEnd": "31/12",
  "kaupapaMaori": null,
  "pasifika": null,
  "social": {
    "facebook": null,
    "twitter": null
  },
  "lastUpdated": "2018-01-09T01:24:46Z"
}