{
  "id": 41836,
  "registrationNumber": "CC26212",
  "name": "Nga Pekanga Te Kohanga Reo",
  "status": "Registered",
  "type": "0",
  "dateRegistered": "2008-06-18T00:00:00Z",
  "dateDeregistered": null,
  "website": null,
  "email": "whanau@k07a022.kohanga.ac.nz",
  "address": {
    "line1": "35A Princess Street",
    "line2": "Waitara 4320",
    "suburb": " ",
    "city": "Waitara",
    "postcode": "4320"
  },
  "nzbn": null,
  "financialYearEnd": "31/12",
  "kaupapaMaori": null,
  "pasifika": null,
  "social": {
    "facebook": null,
    "twitter": null
  },
  "lastUpdated": "2025-04-14T19:44:54Z"
}