{
  "id": 59832,
  "registrationNumber": "CC27628",
  "name": "Breakthrough Education Trust",
  "status": "Registered",
  "type": "0",
  "dateRegistered": "2008-06-30T00:00:00Z",
  "dateDeregistered": null,
  "website": "breakthroughoscar.nz",
  "email": "legacy@houseofbreakthrough.com",
  "address": {
    "line1": "7 Potae Avenue",
    "line2": " ",
    "suburb": "Lytton West",
    "city": "Gisborne",
    "postcode": "4010"
  },
  "nzbn": "9429043132652",
  "financialYearEnd": "31/3",
  "kaupapaMaori": true,
  "pasifika": true,
  "social": {
    "facebook": "Breakthrough OSCAR",
    "twitter": null
  },
  "lastUpdated": "2025-09-15T19:21:53Z"
}