{
  "id": 60397,
  "registrationNumber": "CC28415",
  "name": "Onewa Parents Centre Incorporated",
  "status": "Registered",
  "type": "1",
  "dateRegistered": "2008-06-30T00:00:00Z",
  "dateDeregistered": null,
  "website": "http://www.onewaparentscentre.org.nz/",
  "email": "opcantenatal@gmail.com",
  "address": {
    "line1": "33 Rawene Road",
    "line2": " ",
    "suburb": "Birkenhead",
    "city": "Auckland",
    "postcode": "0626"
  },
  "nzbn": "9429042814139",
  "financialYearEnd": "31/3",
  "kaupapaMaori": false,
  "pasifika": false,
  "social": {
    "facebook": "http://www.facebook.com/OnewaParentsCentre",
    "twitter": null
  },
  "lastUpdated": "2026-03-22T06:05:12Z"
}