{
  "id": 60792,
  "registrationNumber": "CC28570",
  "name": "The George Turner Wilson Trust",
  "status": "Registered",
  "type": "0",
  "dateRegistered": "2008-06-30T00:00:00Z",
  "dateDeregistered": null,
  "website": null,
  "email": "colin.bright@jpf.co.nz",
  "address": {
    "line1": "C/o Johnston Prichard Fee Limited",
    "line2": "Level 8, Vero Centre",
    "suburb": "48 Shortland Street",
    "city": "Auckland",
    "postcode": "1010"
  },
  "nzbn": null,
  "financialYearEnd": "31/3",
  "kaupapaMaori": false,
  "pasifika": false,
  "social": {
    "facebook": null,
    "twitter": null
  },
  "lastUpdated": "2025-08-27T19:19:36Z"
}