{
  "id": 39429,
  "registrationNumber": "CC28532",
  "name": "Estate of William Weir",
  "status": "Registered",
  "type": "0",
  "dateRegistered": "2008-06-30T00:00:00Z",
  "dateDeregistered": null,
  "website": "www.publictrust.co.nz",
  "email": "funding@publictrust.co.nz",
  "address": {
    "line1": "Public Trust Tower",
    "line2": "22 Willeston Street",
    "suburb": "Wellington Central",
    "city": "Wellington",
    "postcode": "6011"
  },
  "nzbn": null,
  "financialYearEnd": "30/9",
  "kaupapaMaori": false,
  "pasifika": false,
  "social": {
    "facebook": null,
    "twitter": null
  },
  "lastUpdated": "2025-11-03T22:06:08Z"
}