{
  "id": 60375,
  "registrationNumber": "CC29598",
  "name": "Rotary Club Of Kawerau Charitable Trust",
  "status": "Registered",
  "type": "0",
  "dateRegistered": "2008-06-30T00:00:00Z",
  "dateDeregistered": null,
  "website": null,
  "email": "gail.dobbin@xtra.co.nz",
  "address": {
    "line1": "403 River Road",
    "line2": null,
    "suburb": " ",
    "city": "Kawerau",
    "postcode": "3127"
  },
  "nzbn": "9429043163793",
  "financialYearEnd": "30/6",
  "kaupapaMaori": false,
  "pasifika": false,
  "social": {
    "facebook": null,
    "twitter": null
  },
  "lastUpdated": "2026-02-18T23:25:11Z"
}