{
  "id": 64902,
  "registrationNumber": "CC30199",
  "name": "The Jones Missionary Trust Fund",
  "status": "Registered",
  "type": "0",
  "dateRegistered": "2008-06-30T00:00:00Z",
  "dateDeregistered": null,
  "website": null,
  "email": "jgweir@yrless.co.nz",
  "address": {
    "line1": "28 North Terrace",
    "line2": null,
    "suburb": " ",
    "city": "Gore",
    "postcode": "9710"
  },
  "nzbn": null,
  "financialYearEnd": "31/5",
  "kaupapaMaori": false,
  "pasifika": false,
  "social": {
    "facebook": null,
    "twitter": null
  },
  "lastUpdated": "2025-08-20T19:51:12Z"
}