{
  "id": 48408,
  "registrationNumber": "CC30683",
  "name": "Tokoroa Childcare Centre Incorporated",
  "status": "Registered",
  "type": "1",
  "dateRegistered": "2008-06-30T00:00:00Z",
  "dateDeregistered": null,
  "website": null,
  "email": "elvisa.vanderleden@gmail.com",
  "address": {
    "line1": "50 Maraetai Road",
    "line2": null,
    "suburb": " ",
    "city": "Tokoroa",
    "postcode": "3420"
  },
  "nzbn": "9429042885399",
  "financialYearEnd": "31/3",
  "kaupapaMaori": false,
  "pasifika": false,
  "social": {
    "facebook": null,
    "twitter": null
  },
  "lastUpdated": "2026-03-20T01:48:42Z"
}