{
  "id": 48387,
  "registrationNumber": "CC31667",
  "name": "Palmerston North Tramping and Mountaineering Club Incorporated",
  "status": "Registered",
  "type": "1",
  "dateRegistered": "2008-06-30T00:00:00Z",
  "dateDeregistered": null,
  "website": "https://www.pntmc.org.nz",
  "email": "pntmci@gmail.com",
  "address": {
    "line1": "227 College Street",
    "line2": " ",
    "suburb": "West End",
    "city": "Palmerston North",
    "postcode": "4412"
  },
  "nzbn": "9429042819516",
  "financialYearEnd": "28/2",
  "kaupapaMaori": false,
  "pasifika": false,
  "social": {
    "facebook": "https://www.facebook.com/Palmerston-North-Tramping-and-Mountaineering-Club-1577289419011545/",
    "twitter": null
  },
  "lastUpdated": "2025-10-17T01:11:10Z"
}