{
  "id": 39366,
  "registrationNumber": "CC31516",
  "name": "Te Whanau Whakapono (Faith Family Centre) Whakatane Fellowship",
  "status": "Deregistered",
  "type": "1",
  "dateRegistered": "2008-06-30T00:00:00Z",
  "dateDeregistered": "2010-05-04T00:00:00Z",
  "website": "http://www.mmhn.co.nz",
  "email": "mkatipa@e3.net.nz",
  "address": {
    "line1": "16 Wairaka Road",
    "line2": "Po Box 180",
    "suburb": null,
    "city": "Whakatane",
    "postcode": "3080"
  },
  "nzbn": null,
  "financialYearEnd": "31/3",
  "kaupapaMaori": null,
  "pasifika": null,
  "social": {
    "facebook": null,
    "twitter": null
  },
  "lastUpdated": "2018-01-09T02:04:49Z"
}