{
  "id": 43793,
  "registrationNumber": "CC32870",
  "name": "Anaura Associates Trust",
  "status": "Deregistered",
  "type": "0",
  "dateRegistered": "2008-06-30T00:00:00Z",
  "dateDeregistered": "2017-03-05T00:00:00Z",
  "website": null,
  "email": null,
  "address": {
    "line1": "890 Anaura Road",
    "line2": "RD 1",
    "suburb": null,
    "city": "Tokomaru Bay",
    "postcode": "4079"
  },
  "nzbn": "9429043005413",
  "financialYearEnd": "31/3",
  "kaupapaMaori": null,
  "pasifika": null,
  "social": {
    "facebook": null,
    "twitter": null
  },
  "lastUpdated": "2018-01-09T02:13:10Z"
}