{
  "id": 57938,
  "registrationNumber": "CC32429",
  "name": "Linking Hands Incorporated",
  "status": "Registered",
  "type": "1",
  "dateRegistered": "2008-06-30T00:00:00Z",
  "dateDeregistered": null,
  "website": "https://www.linkinghands.co.nz",
  "email": "linkinghandsmain@gmail.com",
  "address": {
    "line1": "131 Hurndall Street East",
    "line2": null,
    "suburb": " ",
    "city": "Maungaturoto",
    "postcode": "0520"
  },
  "nzbn": "9429043160655",
  "financialYearEnd": "31/3",
  "kaupapaMaori": false,
  "pasifika": false,
  "social": {
    "facebook": "Linking Hands Incorporated",
    "twitter": null
  },
  "lastUpdated": "2026-02-13T00:12:09Z"
}