{
  "id": 44649,
  "registrationNumber": "CC32833",
  "name": "Mangawhai Harbour Restoration Society Incorporated",
  "status": "Registered",
  "type": "0",
  "dateRegistered": "2008-06-30T00:00:00Z",
  "dateDeregistered": null,
  "website": "http://www.mangawhaiharbourrestoration.co.nz",
  "email": "mhrsoc@gmail.com",
  "address": {
    "line1": "115 Black Swamp Road",
    "line2": "Mangawhai 0975",
    "suburb": "Mangawhai",
    "city": "Mangawhai",
    "postcode": "0975"
  },
  "nzbn": "9429042759119",
  "financialYearEnd": "31/3",
  "kaupapaMaori": false,
  "pasifika": false,
  "social": {
    "facebook": "https://www.facebook.com/mangawhaiharbour",
    "twitter": null
  },
  "lastUpdated": "2025-09-23T00:55:43Z"
}