{
  "id": 61502,
  "registrationNumber": "CC34152",
  "name": "The Onehunga Combined Sports Trust",
  "status": "Deregistered",
  "type": "0",
  "dateRegistered": "2008-06-30T00:00:00Z",
  "dateDeregistered": "2019-04-04T00:00:00Z",
  "website": null,
  "email": "waikarakasports@gmail.com",
  "address": {
    "line1": "175-243 Neilson Street",
    "line2": "Onehunga - Te Papa",
    "suburb": " ",
    "city": "Auckland",
    "postcode": "1061"
  },
  "nzbn": "9429043076833",
  "financialYearEnd": "31/12",
  "kaupapaMaori": null,
  "pasifika": null,
  "social": {
    "facebook": null,
    "twitter": null
  },
  "lastUpdated": "2020-05-10T02:07:27Z"
}