{
  "id": 49100,
  "registrationNumber": "CC35742",
  "name": "Fairhaven Fundraising Association",
  "status": "Deregistered",
  "type": "1",
  "dateRegistered": "2008-06-30T00:00:00Z",
  "dateDeregistered": "2010-05-12T00:00:00Z",
  "website": null,
  "email": "waybarbain@value.net.nz",
  "address": {
    "line1": "120 Boucher Avenue",
    "line2": null,
    "suburb": null,
    "city": "Te Puke",
    "postcode": "3119"
  },
  "nzbn": null,
  "financialYearEnd": "31/3",
  "kaupapaMaori": null,
  "pasifika": null,
  "social": {
    "facebook": null,
    "twitter": null
  },
  "lastUpdated": "2018-01-09T02:30:20Z"
}