{
  "id": 39351,
  "registrationNumber": "CC35653",
  "name": "Albury Water Supply Society Incorporated",
  "status": "Registered",
  "type": "1",
  "dateRegistered": "2008-06-30T00:00:00Z",
  "dateDeregistered": null,
  "website": null,
  "email": "albury.water@outlook.co.nz",
  "address": {
    "line1": "444 Mt Nessing Road",
    "line2": "Albury 7984",
    "suburb": "Albury",
    "city": "Albury",
    "postcode": "7984"
  },
  "nzbn": "9429042998822",
  "financialYearEnd": "30/6",
  "kaupapaMaori": false,
  "pasifika": false,
  "social": {
    "facebook": "https://www.facebook.com/Alburywater/",
    "twitter": null
  },
  "lastUpdated": "2025-12-23T18:28:26Z"
}