{
  "id": 41801,
  "registrationNumber": "CC36540",
  "name": "International Association for Natural Gas Vehicles Incorporated",
  "status": "Deregistered",
  "type": "1",
  "dateRegistered": "2008-06-30T00:00:00Z",
  "dateDeregistered": "2022-04-27T00:00:00Z",
  "website": "http://www.iangv.org",
  "email": "bsmith@ngvglobal.org",
  "address": {
    "line1": "19C Warrington Road",
    "line2": null,
    "suburb": "Remuera",
    "city": "Auckland",
    "postcode": "1050"
  },
  "nzbn": "9429042621867",
  "financialYearEnd": "31/12",
  "kaupapaMaori": null,
  "pasifika": null,
  "social": {
    "facebook": null,
    "twitter": null
  },
  "lastUpdated": "2022-04-27T00:40:41Z"
}