{
  "id": 41243,
  "registrationNumber": "CC36206",
  "name": "Central Hawkes Bay Dirt Bike Riders Club",
  "status": "Deregistered",
  "type": "1",
  "dateRegistered": "2008-06-30T00:00:00Z",
  "dateDeregistered": "2017-07-18T00:00:00Z",
  "website": null,
  "email": "kirstpaul98@hotmail.com",
  "address": {
    "line1": "19 Phillips Street",
    "line2": "RD 3",
    "suburb": null,
    "city": "Tikokino",
    "postcode": "4273"
  },
  "nzbn": null,
  "financialYearEnd": "31/5",
  "kaupapaMaori": null,
  "pasifika": null,
  "social": {
    "facebook": null,
    "twitter": null
  },
  "lastUpdated": "2025-10-30T02:06:03Z"
}