{
  "id": 47983,
  "registrationNumber": "CC37495",
  "name": "Ostend Ratepayers Hall Trust Board",
  "status": "Registered",
  "type": "0",
  "dateRegistered": "2008-06-30T00:00:00Z",
  "dateDeregistered": null,
  "website": null,
  "email": "billkinghorn2012@gmail.com",
  "address": {
    "line1": "21 Albert Crescent",
    "line2": " ",
    "suburb": "Ostend",
    "city": "Waiheke Island",
    "postcode": "1081"
  },
  "nzbn": "9429042905042",
  "financialYearEnd": "31/3",
  "kaupapaMaori": false,
  "pasifika": false,
  "social": {
    "facebook": null,
    "twitter": null
  },
  "lastUpdated": "2025-09-24T19:19:57Z"
}