{
  "id": 39066,
  "registrationNumber": "CC37991",
  "name": "Shirley Community Centre Society Incorporated",
  "status": "Deregistered",
  "type": "1",
  "dateRegistered": "2008-06-30T00:00:00Z",
  "dateDeregistered": "2015-02-24T00:00:00Z",
  "website": null,
  "email": "dennis@cyberxpress.co.nz",
  "address": {
    "line1": "29 Kenwyn Avenue",
    "line2": null,
    "suburb": "Saint Albans",
    "city": "Christchurch",
    "postcode": "8052"
  },
  "nzbn": "9429042745464",
  "financialYearEnd": "31/3",
  "kaupapaMaori": null,
  "pasifika": null,
  "social": {
    "facebook": null,
    "twitter": null
  },
  "lastUpdated": "2018-01-09T02:51:26Z"
}