{
  "id": 62936,
  "registrationNumber": "CC38178",
  "name": "Nova Charitable Trust",
  "status": "Registered",
  "type": "0",
  "dateRegistered": "2009-03-02T00:00:00Z",
  "dateDeregistered": null,
  "website": "www.publictrust.co.nz",
  "email": "funding@publictrust.co.nz",
  "address": {
    "line1": "Public Trust Tower",
    "line2": "Level 2",
    "suburb": "22 Willeston Street",
    "city": "Wellington",
    "postcode": "6011"
  },
  "nzbn": null,
  "financialYearEnd": "31/10",
  "kaupapaMaori": false,
  "pasifika": false,
  "social": {
    "facebook": null,
    "twitter": null
  },
  "lastUpdated": "2025-12-21T20:31:43Z"
}