{
  "id": 45333,
  "registrationNumber": "CC40445",
  "name": "Friendly Support Network Central Districts Incorporated",
  "status": "Deregistered",
  "type": "1",
  "dateRegistered": "2008-06-30T00:00:00Z",
  "dateDeregistered": "2021-07-08T00:00:00Z",
  "website": null,
  "email": "vanbrakel@inspire.net.nz",
  "address": {
    "line1": "621 Ferguson Street",
    "line2": " ",
    "suburb": "Terrace End",
    "city": "Palmerston North",
    "postcode": "4410"
  },
  "nzbn": "9429042697688",
  "financialYearEnd": "31/3",
  "kaupapaMaori": null,
  "pasifika": null,
  "social": {
    "facebook": null,
    "twitter": null
  },
  "lastUpdated": "2021-07-26T02:14:08Z"
}