{
  "id": 44952,
  "registrationNumber": "CC40372",
  "name": "Waitakere Special Needs Trust",
  "status": "Deregistered",
  "type": "0",
  "dateRegistered": "2008-06-30T00:00:00Z",
  "dateDeregistered": "2010-11-08T00:00:00Z",
  "website": "http://www.arohanui.school.nz",
  "email": "pat@arohanui.school.nz",
  "address": {
    "line1": "C/- Arohanui Special School",
    "line2": "Tirimoana Road",
    "suburb": "Te Atatu South",
    "city": "Auckland",
    "postcode": "0602"
  },
  "nzbn": "9429042947165",
  "financialYearEnd": "31/12",
  "kaupapaMaori": null,
  "pasifika": null,
  "social": {
    "facebook": null,
    "twitter": null
  },
  "lastUpdated": "2018-01-09T03:06:25Z"
}