{
  "id": 37593,
  "registrationNumber": "CC44630",
  "name": "The Methodist Church of New Zealand Te Haahi Weteriana O Aotearoa Lower North Island Synod (4000)",
  "status": "Registered",
  "type": "1",
  "dateRegistered": "2010-07-13T00:00:00Z",
  "dateDeregistered": null,
  "website": "http://www.methodist.org.nz",
  "email": "treasurer.lnis@methodist.org.nz",
  "address": {
    "line1": "8A Fernwood Court",
    "line2": " ",
    "suburb": "Woodridge",
    "city": "Wellington",
    "postcode": "6037"
  },
  "nzbn": null,
  "financialYearEnd": "30/6",
  "kaupapaMaori": false,
  "pasifika": false,
  "social": {
    "facebook": null,
    "twitter": null
  },
  "lastUpdated": "2026-01-14T00:19:18Z"
}