{
  "id": 35743,
  "registrationNumber": "CC44774",
  "name": "The Scoliosis Research Trust",
  "status": "Deregistered",
  "type": "0",
  "dateRegistered": "2010-07-27T00:00:00Z",
  "dateDeregistered": "2025-11-14T00:00:00Z",
  "website": null,
  "email": "otago@markhams.co.nz",
  "address": {
    "line1": "PO Box 919",
    "line2": " ",
    "suburb": "Dunedin Central",
    "city": "Dunedin",
    "postcode": "9054"
  },
  "nzbn": null,
  "financialYearEnd": "31/3",
  "kaupapaMaori": false,
  "pasifika": false,
  "social": {
    "facebook": null,
    "twitter": null
  },
  "lastUpdated": "2025-11-20T06:04:04Z"
}