{
  "id": 36069,
  "registrationNumber": "CC45264",
  "name": "Waterlea School Parent Teachers Association",
  "status": "Registered",
  "type": "1",
  "dateRegistered": "2010-09-07T00:00:00Z",
  "dateDeregistered": null,
  "website": null,
  "email": "waterleapta@gmail.com",
  "address": {
    "line1": "Waterlea Public School",
    "line2": "17 House Avenue",
    "suburb": "Mangere Bridge",
    "city": "Auckland",
    "postcode": "2022"
  },
  "nzbn": null,
  "financialYearEnd": "31/12",
  "kaupapaMaori": null,
  "pasifika": null,
  "social": {
    "facebook": null,
    "twitter": null
  },
  "lastUpdated": "2025-05-19T06:56:42Z"
}