{
  "id": 36380,
  "registrationNumber": "CC46166",
  "name": "Southland Coastguard Air Patrol Incorporated",
  "status": "Deregistered",
  "type": "1",
  "dateRegistered": "2011-02-13T00:00:00Z",
  "dateDeregistered": "2017-04-30T00:00:00Z",
  "website": "http://www.southernwings.co.nz",
  "email": "tony.dawson@southernwings.co.nz",
  "address": {
    "line1": "76 Airport Avenue",
    "line2": "RD 9",
    "suburb": null,
    "city": "Invercargill",
    "postcode": "9879"
  },
  "nzbn": "9429042955399",
  "financialYearEnd": "31/3",
  "kaupapaMaori": null,
  "pasifika": null,
  "social": {
    "facebook": null,
    "twitter": null
  },
  "lastUpdated": "2018-01-09T03:43:07Z"
}