{
  "id": 38101,
  "registrationNumber": "CC46291",
  "name": "Manukau Maori Wardens Trust",
  "status": "Deregistered",
  "type": "0",
  "dateRegistered": "2011-03-07T00:00:00Z",
  "dateDeregistered": "2015-01-26T00:00:00Z",
  "website": null,
  "email": "manukaumaoriwardens@hotmail.com",
  "address": {
    "line1": "PO Box 97306",
    "line2": "Manukau City",
    "suburb": "Auckland",
    "city": null,
    "postcode": "2241"
  },
  "nzbn": "9429043287925",
  "financialYearEnd": "31/3",
  "kaupapaMaori": null,
  "pasifika": null,
  "social": {
    "facebook": null,
    "twitter": null
  },
  "lastUpdated": "2018-01-09T03:43:59Z"
}