{
  "id": 35459,
  "registrationNumber": "CC47079",
  "name": "Rotary Club of Waipapa Charitable Trust",
  "status": "Registered",
  "type": "0",
  "dateRegistered": "2011-07-06T00:00:00Z",
  "dateDeregistered": null,
  "website": null,
  "email": "stephen.hunt@xtra.co.nz",
  "address": {
    "line1": "PO Box 59",
    "line2": null,
    "suburb": " ",
    "city": "Waipapa",
    "postcode": "246"
  },
  "nzbn": null,
  "financialYearEnd": "30/6",
  "kaupapaMaori": false,
  "pasifika": false,
  "social": {
    "facebook": null,
    "twitter": null
  },
  "lastUpdated": "2025-12-02T00:04:34Z"
}