{
  "id": 36569,
  "registrationNumber": "CC47365",
  "name": "Coromandel Peninsula Community Medical Emergency And Air Support Trust",
  "status": "Deregistered",
  "type": "0",
  "dateRegistered": "2012-02-14T00:00:00Z",
  "dateDeregistered": "2013-10-20T00:00:00Z",
  "website": null,
  "email": "john.hart@tax-trusts.com",
  "address": {
    "line1": "PO Box 6011",
    "line2": "Wellesley Street",
    "suburb": "Auckland",
    "city": null,
    "postcode": "1141"
  },
  "nzbn": null,
  "financialYearEnd": "31/3",
  "kaupapaMaori": null,
  "pasifika": null,
  "social": {
    "facebook": null,
    "twitter": null
  },
  "lastUpdated": "2018-01-09T03:51:34Z"
}