{
  "id": 34917,
  "registrationNumber": "CC49070",
  "name": "Hawarden-Waikari Community Trust",
  "status": "Registered",
  "type": "0",
  "dateRegistered": "2013-04-23T00:00:00Z",
  "dateDeregistered": null,
  "website": null,
  "email": "simon.sam@xtra.co.nz",
  "address": {
    "line1": "c/- 148 Victoria Street",
    "line2": null,
    "suburb": " ",
    "city": "Christchurch",
    "postcode": "8013"
  },
  "nzbn": "9429043241972",
  "financialYearEnd": "31/3",
  "kaupapaMaori": false,
  "pasifika": false,
  "social": {
    "facebook": null,
    "twitter": null
  },
  "lastUpdated": "2026-01-08T02:42:16Z"
}