{
  "id": 35259,
  "registrationNumber": "CC49443",
  "name": "Pauanui Surf Life Saving Club Incorporated",
  "status": "Registered",
  "type": "1",
  "dateRegistered": "2013-07-12T00:00:00Z",
  "dateDeregistered": null,
  "website": "https://pauanuilifeguards.org.nz",
  "email": "gavin@cooperaitken.co.nz",
  "address": {
    "line1": "Pauanui Boulevard",
    "line2": "Pauanui Beach",
    "suburb": " ",
    "city": "Pauanui",
    "postcode": "3579"
  },
  "nzbn": "9429042943082",
  "financialYearEnd": "30/6",
  "kaupapaMaori": false,
  "pasifika": false,
  "social": {
    "facebook": null,
    "twitter": null
  },
  "lastUpdated": "2025-10-24T01:32:00Z"
}