{
  "id": 34387,
  "registrationNumber": "CC50690",
  "name": "Friends of East Indonesia",
  "status": "Deregistered",
  "type": "0",
  "dateRegistered": "2014-06-27T00:00:00Z",
  "dateDeregistered": "2020-08-16T00:00:00Z",
  "website": null,
  "email": "friendsofeastindo@gmail.com",
  "address": {
    "line1": "1 Summer Lane",
    "line2": null,
    "suburb": " ",
    "city": "Tairua",
    "postcode": "3508"
  },
  "nzbn": null,
  "financialYearEnd": "31/8",
  "kaupapaMaori": null,
  "pasifika": null,
  "social": {
    "facebook": "https://www.facebook.com/FriendsOfEastIndonesia/",
    "twitter": null
  },
  "lastUpdated": "2020-08-19T23:28:17Z"
}