{
  "id": 34239,
  "registrationNumber": "CC50532",
  "name": "Free to a Good Home",
  "status": "Deregistered",
  "type": "0",
  "dateRegistered": "2014-05-01T00:00:00Z",
  "dateDeregistered": "2017-03-09T00:00:00Z",
  "website": null,
  "email": "helpthehutt@gmail.com",
  "address": {
    "line1": "124 Pinehaven Road",
    "line2": "Pinehaven",
    "suburb": "Upper Hutt",
    "city": "Upper Hutt",
    "postcode": "5019"
  },
  "nzbn": "9429043263325",
  "financialYearEnd": "31/3",
  "kaupapaMaori": null,
  "pasifika": null,
  "social": {
    "facebook": null,
    "twitter": null
  },
  "lastUpdated": "2018-01-09T04:12:44Z"
}