{
  "id": 34218,
  "registrationNumber": "CC50819",
  "name": "Marlborough Basketball Association Incorporated",
  "status": "Registered",
  "type": "1",
  "dateRegistered": "2014-04-16T00:00:00Z",
  "dateDeregistered": null,
  "website": "https://www.marlborough.basketball",
  "email": "simon1@actrix.co.nz",
  "address": {
    "line1": "C/- Marlborough Lines Stadium 2000",
    "line2": "Kinross Street",
    "suburb": " ",
    "city": "Blenheim",
    "postcode": "7201"
  },
  "nzbn": "9429042755180",
  "financialYearEnd": "31/3",
  "kaupapaMaori": false,
  "pasifika": false,
  "social": {
    "facebook": "Facebook.com/MarlboroughBasketball",
    "twitter": null
  },
  "lastUpdated": "2025-10-23T19:09:52Z"
}