{
  "id": 34478,
  "registrationNumber": "CC50814",
  "name": "New Zealand At Venice Biennale Charitable Trust",
  "status": "Registered",
  "type": "0",
  "dateRegistered": "2014-07-04T00:00:00Z",
  "dateDeregistered": null,
  "website": null,
  "email": "leigh@artandobject.co.nz",
  "address": {
    "line1": "2 Stratford Street",
    "line2": " ",
    "suburb": "Parnell",
    "city": "Auckland",
    "postcode": "1052"
  },
  "nzbn": null,
  "financialYearEnd": "31/3",
  "kaupapaMaori": false,
  "pasifika": false,
  "social": {
    "facebook": null,
    "twitter": null
  },
  "lastUpdated": "2025-11-04T19:00:57Z"
}