{
  "id": 34522,
  "registrationNumber": "CC50904",
  "name": "J & A Mauger Charitable Trust",
  "status": "Deregistered",
  "type": "0",
  "dateRegistered": "2014-07-21T00:00:00Z",
  "dateDeregistered": "2021-03-31T00:00:00Z",
  "website": "http://www.trustees.co.nz",
  "email": "accounting@trustees.co.nz",
  "address": {
    "line1": "24 Water Street",
    "line2": " ",
    "suburb": "Dunedin Central",
    "city": "Dunedin",
    "postcode": "9016"
  },
  "nzbn": null,
  "financialYearEnd": "31/3",
  "kaupapaMaori": null,
  "pasifika": null,
  "social": {
    "facebook": null,
    "twitter": null
  },
  "lastUpdated": "2024-06-17T21:05:21Z"
}