{
  "id": 65317,
  "registrationNumber": "CC51544",
  "name": "St Marks Foundation",
  "status": "Deregistered",
  "type": "0",
  "dateRegistered": "2015-04-14T00:00:00Z",
  "dateDeregistered": "2019-05-31T00:00:00Z",
  "website": "https://www.saintmarks.school.nz",
  "email": "chairperson@saintmarks.bop.nz",
  "address": {
    "line1": "33 Cholmondeley Avenue",
    "line2": " ",
    "suburb": "Opawa",
    "city": "Christchurch",
    "postcode": "8023"
  },
  "nzbn": "9429043020423",
  "financialYearEnd": "31/5",
  "kaupapaMaori": null,
  "pasifika": null,
  "social": {
    "facebook": null,
    "twitter": null
  },
  "lastUpdated": "2024-05-22T23:23:37Z"
}