{
  "id": 67102,
  "registrationNumber": "CC53379",
  "name": "Waiariki Literacy Association",
  "status": "Deregistered",
  "type": null,
  "dateRegistered": "2016-06-07T00:00:00Z",
  "dateDeregistered": "2020-06-30T00:00:00Z",
  "website": "part of  'nzla.org.nz' website",
  "email": "triciakenyon@xtra.co.nz",
  "address": {
    "line1": "184 Central Road",
    "line2": " ",
    "suburb": "RD 6",
    "city": "Rotorua",
    "postcode": "3096"
  },
  "nzbn": null,
  "financialYearEnd": "31/12",
  "kaupapaMaori": null,
  "pasifika": null,
  "social": {
    "facebook": "Waiariki Literacy Association@waiarikiliteracyassociation",
    "twitter": null
  },
  "lastUpdated": "2020-08-19T23:17:50Z"
}