{
  "id": 66754,
  "registrationNumber": "CC53026",
  "name": "Far North Resilient Communities Charitable Trust",
  "status": "Registered",
  "type": "0",
  "dateRegistered": "2015-08-17T00:00:00Z",
  "dateDeregistered": null,
  "website": "https://resilientcommunitiesfn.co.nz/",
  "email": "di@resilientcommunitiesfn.co.nz",
  "address": {
    "line1": "49D McCaughan Road",
    "line2": "RD 1",
    "suburb": " ",
    "city": "Kerikeri",
    "postcode": "0294"
  },
  "nzbn": "9429051800574",
  "financialYearEnd": "30/6",
  "kaupapaMaori": false,
  "pasifika": false,
  "social": {
    "facebook": null,
    "twitter": null
  },
  "lastUpdated": "2026-02-17T04:50:20Z"
}