{
  "id": 68038,
  "registrationNumber": "CC54367",
  "name": "Te Ao Marama Whakaihuwaka C3A Homestead",
  "status": "Deregistered",
  "type": null,
  "dateRegistered": "2017-03-03T00:00:00Z",
  "dateDeregistered": "2018-08-21T00:00:00Z",
  "website": null,
  "email": "kiwiroamers@hotmail.com",
  "address": {
    "line1": "Flat 2",
    "line2": "162 Pigeon Mountain Road",
    "suburb": "Half Moon Bay",
    "city": "Auckland",
    "postcode": "2012"
  },
  "nzbn": null,
  "financialYearEnd": "31/3",
  "kaupapaMaori": null,
  "pasifika": null,
  "social": {
    "facebook": "Te Aomarama Whakaihuwaka Homestead",
    "twitter": null
  },
  "lastUpdated": "2023-05-15T03:12:46Z"
}