{
  "id": 67874,
  "registrationNumber": "CC54184",
  "name": "Food Rescue Northland - Kai Whakaora",
  "status": "Deregistered",
  "type": null,
  "dateRegistered": "2016-12-23T00:00:00Z",
  "dateDeregistered": "2024-01-25T00:00:00Z",
  "website": "https://foodrescuenorthland.nz/",
  "email": "155.carol.peters@gmail.com",
  "address": {
    "line1": "1 Woods Road",
    "line2": "Whangarei 0110",
    "suburb": " ",
    "city": "Whangarei",
    "postcode": "0110"
  },
  "nzbn": "9429045889349",
  "financialYearEnd": "30/6",
  "kaupapaMaori": null,
  "pasifika": null,
  "social": {
    "facebook": "https://www.facebook.com/Whakaora-Kai-Taitokerau-Food-Rescue-Northland-171162166776472/",
    "twitter": null
  },
  "lastUpdated": "2026-01-07T06:04:25Z"
}