{
  "id": 68611,
  "registrationNumber": "CC54947",
  "name": "Canterbury Older Persons Welfare Trust",
  "status": "Registered",
  "type": null,
  "dateRegistered": "2017-08-22T00:00:00Z",
  "dateDeregistered": null,
  "website": "https://www.ageconcerncan.org.nz",
  "email": "ceo@ageconcerncan.org.nz",
  "address": {
    "line1": "24 Main North Road",
    "line2": " ",
    "suburb": "Papanui",
    "city": "Christchurch",
    "postcode": "8053"
  },
  "nzbn": "9429045986024",
  "financialYearEnd": "31/3",
  "kaupapaMaori": null,
  "pasifika": null,
  "social": {
    "facebook": "www.facebook.com/Age-concern-Canterbury",
    "twitter": null
  },
  "lastUpdated": "2025-08-23T03:35:14Z"
}