{
  "id": 68705,
  "registrationNumber": "CC55045",
  "name": "Mahurangi Wastebusters Trust",
  "status": "Registered",
  "type": null,
  "dateRegistered": "2017-12-15T00:00:00Z",
  "dateDeregistered": null,
  "website": null,
  "email": "trishallennz@gmail.com",
  "address": {
    "line1": "15 Courtney Lane",
    "line2": "RD 5",
    "suburb": "Matakana",
    "city": "Warkworth",
    "postcode": "0985"
  },
  "nzbn": "9429047272637",
  "financialYearEnd": "31/3",
  "kaupapaMaori": false,
  "pasifika": false,
  "social": {
    "facebook": "Mahurangi Wastebusters",
    "twitter": null
  },
  "lastUpdated": "2025-09-30T19:08:33Z"
}