{
  "id": 69246,
  "registrationNumber": "CC55594",
  "name": "Sosaiete o Aoga Amata Samoa I Aotearoa Incorporated",
  "status": "Registered",
  "type": "1",
  "dateRegistered": "2018-08-03T00:00:00Z",
  "dateDeregistered": null,
  "website": "https://www.saasia.org",
  "email": "lanuola.moe@gmail.com",
  "address": {
    "line1": "Māngere Old School Hall",
    "line2": "299 Kirkbride Road",
    "suburb": "Mangere",
    "city": "Auckland",
    "postcode": "2022"
  },
  "nzbn": "9429043123780",
  "financialYearEnd": "30/6",
  "kaupapaMaori": false,
  "pasifika": true,
  "social": {
    "facebook": "https://www.facebook.com/saasiainc",
    "twitter": null
  },
  "lastUpdated": "2025-11-26T04:07:14Z"
}