{
  "id": 71123,
  "registrationNumber": "CC57495",
  "name": "Taiji International Traditional Chinese Medicine Foundation",
  "status": "Registered",
  "type": null,
  "dateRegistered": "2019-09-11T00:00:00Z",
  "dateDeregistered": null,
  "website": "https://www.tcmfoundations.com",
  "email": "dawson.001@hotmail.com",
  "address": {
    "line1": "34 Bank Street",
    "line2": " ",
    "suburb": "North East Valley",
    "city": "Dunedin",
    "postcode": "9010"
  },
  "nzbn": "9429050900121",
  "financialYearEnd": "31/3",
  "kaupapaMaori": null,
  "pasifika": null,
  "social": {
    "facebook": "https://www.facebook.com/groups/963194571101002",
    "twitter": null
  },
  "lastUpdated": "2025-07-29T19:26:44Z"
}