{
  "id": 71576,
  "registrationNumber": "CC57948",
  "name": "Carterton Village Charitable Trust",
  "status": "Registered",
  "type": null,
  "dateRegistered": "2020-06-11T00:00:00Z",
  "dateDeregistered": null,
  "website": null,
  "email": "inu.poutoa@gmail.com",
  "address": {
    "line1": "113A Belvedere Road",
    "line2": null,
    "suburb": " ",
    "city": "Carterton",
    "postcode": "5713"
  },
  "nzbn": null,
  "financialYearEnd": "31/3",
  "kaupapaMaori": false,
  "pasifika": false,
  "social": {
    "facebook": "https://www.facebook.com/CartertonYouthVillageTrust/",
    "twitter": null
  },
  "lastUpdated": "2026-02-17T04:06:13Z"
}