{
  "id": 72406,
  "registrationNumber": "CC58815",
  "name": "Hawke's Bay Justices of the Peace Association Incorporated",
  "status": "Registered",
  "type": null,
  "dateRegistered": "2021-02-10T00:00:00Z",
  "dateDeregistered": null,
  "website": null,
  "email": "reg.hbjpa@gmail.com",
  "address": {
    "line1": "8 Waterhouse Street",
    "line2": " ",
    "suburb": "Taradale",
    "city": "Napier",
    "postcode": "4112"
  },
  "nzbn": null,
  "financialYearEnd": "31/8",
  "kaupapaMaori": false,
  "pasifika": false,
  "social": {
    "facebook": null,
    "twitter": null
  },
  "lastUpdated": "2026-01-11T18:18:28Z"
}