{
  "id": 74574,
  "registrationNumber": "CC60993",
  "name": "Te Upoko Maori Wardens",
  "status": "Registered",
  "type": null,
  "dateRegistered": "2023-02-18T00:00:00Z",
  "dateDeregistered": null,
  "website": null,
  "email": "alister@tuert.org",
  "address": {
    "line1": "8 Clapham Grove",
    "line2": " ",
    "suburb": "Stokes Valley",
    "city": "Lower Hutt",
    "postcode": "5019"
  },
  "nzbn": null,
  "financialYearEnd": "31/3",
  "kaupapaMaori": null,
  "pasifika": null,
  "social": {
    "facebook": null,
    "twitter": null
  },
  "lastUpdated": "2026-03-17T04:30:23Z"
}