{
  "id": 74035,
  "registrationNumber": "CC60444",
  "name": "Hako Tiaki Whenua Trust",
  "status": "Registered",
  "type": null,
  "dateRegistered": "2022-06-21T00:00:00Z",
  "dateDeregistered": "2022-08-23T00:00:00Z",
  "website": null,
  "email": "sam@whakauka.org",
  "address": {
    "line1": "46 Tukaki Road",
    "line2": "Tirohia 3673",
    "suburb": " ",
    "city": "Tirohia",
    "postcode": "3673"
  },
  "nzbn": "9429050422920",
  "financialYearEnd": "30/6",
  "kaupapaMaori": true,
  "pasifika": false,
  "social": {
    "facebook": null,
    "twitter": null
  },
  "lastUpdated": "2025-07-15T22:45:03Z"
}