{
  "id": 74245,
  "registrationNumber": "CC60655",
  "name": "Hawaiki Kura Charitable Trust",
  "status": "Registered",
  "type": null,
  "dateRegistered": "2022-05-06T00:00:00Z",
  "dateDeregistered": null,
  "website": null,
  "email": "kiley@hawaikikura.com",
  "address": {
    "line1": "16 Adams Lane",
    "line2": " ",
    "suburb": "Springlands",
    "city": "Blenheim",
    "postcode": "7201"
  },
  "nzbn": "9429050779123",
  "financialYearEnd": "31/3",
  "kaupapaMaori": null,
  "pasifika": null,
  "social": {
    "facebook": null,
    "twitter": null
  },
  "lastUpdated": "2025-08-18T19:47:16Z"
}