{
  "id": 75740,
  "registrationNumber": "CC62187",
  "name": "Bras and Brass Foundation",
  "status": "Registered",
  "type": null,
  "dateRegistered": "2024-04-24T00:00:00Z",
  "dateDeregistered": null,
  "website": null,
  "email": "trustee@brasandbrass.org.nz",
  "address": {
    "line1": "1 Silverbirch Grove",
    "line2": " ",
    "suburb": "Churton Park",
    "city": "Wellington",
    "postcode": "6037"
  },
  "nzbn": "9429051949600",
  "financialYearEnd": "31/12",
  "kaupapaMaori": false,
  "pasifika": false,
  "social": {
    "facebook": null,
    "twitter": null
  },
  "lastUpdated": "2025-07-13T23:42:23Z"
}