{
  "id": 77936,
  "registrationNumber": "CC63739",
  "name": "TE WHANAU AWAHOU O TE URU KARAKA INCORPORATED",
  "status": "Registered",
  "type": null,
  "dateRegistered": "2025-09-11T00:00:00Z",
  "dateDeregistered": null,
  "website": null,
  "email": "reremcleod@gmail.com",
  "address": {
    "line1": "15 Monmouth Street",
    "line2": " ",
    "suburb": "Grey Lynn",
    "city": "Auckland",
    "postcode": "1021"
  },
  "nzbn": null,
  "financialYearEnd": "31/12",
  "kaupapaMaori": true,
  "pasifika": false,
  "social": {
    "facebook": null,
    "twitter": null
  },
  "lastUpdated": "2025-09-16T02:12:24Z"
}