{
  "id": 78262,
  "registrationNumber": "CC64079",
  "name": "Mana Whaikaha Charitable Trust",
  "status": "Registered",
  "type": null,
  "dateRegistered": "2025-12-22T00:00:00Z",
  "dateDeregistered": null,
  "website": null,
  "email": "pipbrunn@gmail.com",
  "address": {
    "line1": "17 Juliana Place",
    "line2": " ",
    "suburb": "Awapuni",
    "city": "Palmerston North",
    "postcode": "4412"
  },
  "nzbn": null,
  "financialYearEnd": "31/3",
  "kaupapaMaori": false,
  "pasifika": false,
  "social": {
    "facebook": "https://www.facebook.com/EGLMidCentral/",
    "twitter": null
  },
  "lastUpdated": "2026-03-03T20:22:14Z"
}